virtual_dataframe/__init__.py
virtual_dataframe/_version.py
virtual_dataframe/env.py
virtual_dataframe/py.typed
virtual_dataframe/vclient.py
virtual_dataframe/vlocalcluster.py
virtual_dataframe/vpandas.py
virtual_dataframe/bin/__init__.py
virtual_dataframe/bin/build-conda-vdf-env
virtual_dataframe/bin/virtual_dataframe-all.yml
virtual_dataframe/bin/virtual_dataframe-cudf.yml
virtual_dataframe/bin/virtual_dataframe-dask-local.yml
virtual_dataframe/bin/virtual_dataframe-dask.yml
virtual_dataframe/bin/virtual_dataframe-dask_cudf-local.yml
virtual_dataframe/bin/virtual_dataframe-dask_cudf.yml
virtual_dataframe/bin/virtual_dataframe-dask_modin-local.yml
virtual_dataframe/bin/virtual_dataframe-dask_modin.yml
virtual_dataframe/bin/virtual_dataframe-modin.yml
virtual_dataframe/bin/virtual_dataframe-pandas.yml
virtual_dataframe/bin/virtual_dataframe-pyspark-local.yml
virtual_dataframe/bin/virtual_dataframe-pyspark.yml
virtual_dataframe/bin/virtual_dataframe-pyspark_gpu-local.yml
virtual_dataframe/bin/virtual_dataframe-pyspark_gpu.yml
virtual_dataframe-0.5.dist-info/LICENSE.txt
virtual_dataframe-0.5.dist-info/METADATA
virtual_dataframe-0.5.dist-info/WHEEL
virtual_dataframe-0.5.dist-info/entry_points.txt
virtual_dataframe-0.5.dist-info/top_level.txt
virtual_dataframe-0.5.dist-info/RECORD
