Metadata-Version: 2.1
Name: virtual-dataframe
Version: 0.5
Summary: Bridge between pandas, cudf, modin, dask, dask-modin, dask-cudf, spark or spark+rapids
Home-page: https://github.com/pprados/virtual_dataframe
Author: Philippe Prados
Author-email: github@prados.fr
License: Apache-2.0
Keywords: dataframe
Classifier: Development Status :: 4 - Beta
Classifier: Environment :: Console
Classifier: Intended Audience :: Developers
Classifier: License :: OSI Approved :: Apache Software License
Classifier: Natural Language :: English
Classifier: Programming Language :: Python :: 3.8
Classifier: Operating System :: OS Independent
Classifier: Topic :: Scientific/Engineering
Requires-Python: >=3.8
License-File: LICENSE.txt
Requires-Dist: pandas (>1.4)
Requires-Dist: python-dotenv (>=0.20)
Requires-Dist: GPUtil (>=1.4.0)
